flake8_bandit.py
flake8_bandit-4.1.1.dist-info/LICENSE
flake8_bandit-4.1.1.dist-info/METADATA
flake8_bandit-4.1.1.dist-info/WHEEL
flake8_bandit-4.1.1.dist-info/entry_points.txt
flake8_bandit-4.1.1.dist-info/top_level.txt
flake8_bandit-4.1.1.dist-info/RECORD
