Metadata-Version: 2.1
Name: flake8-bandit
Version: 4.1.1
Summary: Automated security testing with bandit and flake8.
Home-page: https://github.com/tylerwince/flake8-bandit
Author: Tyler Wince
Author-email: tylerwince@gmail.com
License: MIT
Classifier: Framework :: Flake8
Classifier: Environment :: Console
Classifier: Intended Audience :: Developers
Classifier: License :: OSI Approved :: MIT License
Classifier: Programming Language :: Python
Classifier: Programming Language :: Python :: 3
Classifier: Topic :: Security
Classifier: Topic :: Software Development :: Libraries :: Python Modules
Classifier: Topic :: Software Development :: Quality Assurance
Requires-Python: >=3.6
License-File: LICENSE
